py2k/__init__.py
py2k/creators.py
py2k/producer.py
py2k/producer_config.py
py2k/record.py
py2k/serializer.py
py2k/writer.py
py2k/utils/__init__.py
py2k-1.9.1.dist-info/AUTHORS.md
py2k-1.9.1.dist-info/LICENSE
py2k-1.9.1.dist-info/METADATA
py2k-1.9.1.dist-info/WHEEL
py2k-1.9.1.dist-info/top_level.txt
py2k-1.9.1.dist-info/RECORD
