Metadata-Version: 2.1
Name: py2k
Version: 1.9.1
Summary: High level Python API for writing to Kafka
Home-page: https://github.com/AbsaOSS/py2k.git
Author: Daniel Wertheimer
Author-email: daniel.wertheimer@absa.africa
License: Apache Software license
Keywords: py2k
Platform: UNKNOWN
Classifier: Development Status :: 5 - Production/Stable
Classifier: Intended Audience :: Developers
Classifier: License :: OSI Approved :: Apache Software License
Classifier: Natural Language :: English
Classifier: Programming Language :: Python :: 3
Classifier: Programming Language :: Python :: 3.6
Classifier: Programming Language :: Python :: 3.7
Classifier: Programming Language :: Python :: 3.8
Classifier: Programming Language :: Python :: 3.9
Requires-Python: >=3.6
License-File: LICENSE
License-File: AUTHORS.md
Requires-Dist: confluent-kafka[avro] (>=1.5.0)
Requires-Dist: pandas (>=1.1.0)
Requires-Dist: pydantic (>=1.5.1)
Requires-Dist: tqdm (>=4.48.2)
